{
  "id": "sans_hardship",
  "label": "😊 Sans coups durs",
  "description": "Standard complet, sans aucun coup dur",
  "deck": {
    "architecte": 1, "astronaute": 1, "avocat": 1, "bandit": 1, "barman": 1,
    "chef_des_ventes": 1, "chef_des_achats": 1, "chercheur": 1, "chirurgien": 1,
    "designer": 1, "ecrivain": 1, "garagiste": 1, "gourou": 1, "jardinier": 1,
    "journaliste": 1, "medecin": 1, "medium": 1, "militaire": 1, "pharmacien": 1,
    "pilote_de_ligne": 1, "pizzaiolo": 1, "plombier": 1, "policier": 1,
    "prof_anglais": 1, "prof_francais": 1, "prof_histoire": 1, "prof_maths": 1,
    "serveur": 1, "stripteaser": 1, "grand_prof": 1,
    "study_simple": 22, "study_double": 3,
    "salary_1": 10, "salary_2": 10, "salary_3": 10, "salary_4": 10,
    "flirt_bar": 2, "flirt_boite_de_nuit": 2, "flirt_cinema": 2, "flirt_internet": 2,
    "flirt_parc": 2, "flirt_restaurant": 2, "flirt_theatre": 2, "flirt_zoo": 2,
    "flirt_child_camping": 2, "flirt_child_hotel": 2,
    "mariage_corps_nuds": 1, "mariage_montcuq": 1, "mariage_monteton": 1,
    "mariage_sainte_vierge": 1, "mariage_fourqueux": 1, "adultere": 1,
    "child_diana": 1, "child_harry": 1, "child_hermione": 1, "child_lara": 1,
    "child_leia": 1, "child_luigi": 1, "child_luke": 1, "child_mario": 1,
    "child_rocky": 1, "child_zelda": 1,
    "animal_chat": 1, "animal_chien": 1, "animal_lapin": 1,
    "animal_licorne": 1, "animal_poussin": 1,
    "house_petite": 2, "house_moyenne": 2, "house_grande": 1,
    "trip_le_caire": 1, "trip_londres": 1, "trip_new_york": 1,
    "trip_rio": 1, "trip_sydney": 1,
    "troc": 1, "tsunami": 1, "heritage": 1, "piston": 1, "anniversaire": 1,
    "casino": 1, "chance": 1, "etoile_filante": 1, "vengeance": 1, "arc_en_ciel": 1,
    "legion": 1, "price": 2
  }
}